Decodificador Huffman/huffman_dec.sv
module huffman_decoder_serial(input  logic clk,
               input logic rst,
               input  logic in,
               output logic [5:0] huffman_outp);
    logic [7:0] buffer;
    logic [3:0] next_counter,counter;
    logic y;
    parameter [1:0] S1  =       2'b00;
    parameter [1:0] S2  =       2'b01;
    parameter [1:0] S3  =       2'b10;
    parameter [2:0] S4  =      3'b110;
    parameter [5:0] S5  =   6'b111000;
    parameter [5:0] S6  =   6'b111001;
    parameter [5:0] S7  =   6'b111010;
    parameter [6:0] S8  =  7'b1110110;
    parameter [6:0] S9  =  7'b1110111;
    parameter [6:0] S10 =  7'b1111000;
    parameter [6:0] S11 =  7'b1111001;
    parameter [6:0] S12 =  7'b1111010;
    parameter [6:0] S13 =  7'b1111011;
    parameter [6:0] S14 =  7'b1111100;
    parameter [6:0] S15 =  7'b1111101;
    parameter [6:0] S16 =  7'b1111110;
    parameter [7:0] S17 = 8'b11111110;
    parameter [7:0] S18 = 8'b11111111;
    always@(counter)begin
        case(counter)
            4'bzzzz:begin next_counter = 0;
            end
            0:begin next_counter = 1;
                    buffer[7] = in;
                    y = 0;
            end
            1:begin next_counter = 2;
                    buffer[6] = in;
                    case (buffer[7:6])
                    S1:begin
                        huffman_outp = 1;
                        y = 1;
                    end
                    S2:begin
                        huffman_outp = 2;
                        y = 1;
                    end 
                    S3:begin 
                        huffman_outp = 3;
                        y = 1;
                    end
                endcase 
            end
            2:begin next_counter = 3;
                    buffer[5] = in;
                    case(buffer[7:5])
                    S4:begin
                        huffman_outp = 4;
                        y = 1;
                    end
                endcase
                    
            end
            3:begin next_counter = 4;
                    buffer[4] = in;
                    y = 0;
            end
            4:begin next_counter = 5;
                    buffer[3] = in;
                    y = 0;
            end
            5:begin next_counter = 6;
                    buffer[2] = in;
                    case(buffer[7:2])
                    S5:begin
                        huffman_outp = 5;
                        y = 1;
                    end
                    S6:begin
                        huffman_outp = 6;
                        y = 1;
                    end
                    S7:begin
                        huffman_outp = 7;
                        y =1;
                    end
                    default: y = 0;    
                endcase 
                    
            end
            6:begin next_counter = 7;
                buffer[1] = in;
                case(buffer[7:1])//110110
                S8:begin
                    huffman_outp = 8;
                    y = 1;
                end
                S9:begin
                    huffman_outp = 9;
                    y = 1;

                end
                S10:begin
                    huffman_outp = 10;
                    y = 1;

                end
                S11:begin
                    huffman_outp = 11;
                    y = 1;

                end
                S12:begin
                    huffman_outp = 12;
                    y = 1;

                end
                S13:begin
                    huffman_outp = 13;
                    y = 1;

                end
                S14:begin
                    huffman_outp = 14;
                    y = 1;

                end
                S15:begin
                    huffman_outp = 15;
                    y = 1;

                end
                S16:begin
                    huffman_outp = 16;
                    y = 1;
                end
                default: y = 0;
            endcase 

            end
            7:begin next_counter  =4'bzzzz;
                buffer[0] = in;
                case (buffer)
                S17:begin
                    y = 1;
                    huffman_outp = 17;
                end
                S18:begin
                    huffman_outp = 18;
                    y = 1;
                end
                default: y = 0;
                endcase 
            end

        endcase

    end
    always@(posedge clk)begin
        if(rst)begin
            counter <= 4'bzzzz;
        end
        else begin
            counter <= next_counter;
        end
        if(y)begin
            counter <= 0;
        end
    end
endmodule

Decodificador Huffman/testbench_huffman.sv
`include "huffman_dec.sv"
module tb();
    logic clk,in,rst;
    wire [5:0] huffman_outp;
    logic [7:0] i,num;

    huffman_decoder_serial huffman_dec(.clk(clk),.rst(rst),.in(in),.huffman_outp(huffman_outp));
    initial begin
        clk = 0;
        in = 1;
        rst = 1;
        in = 1'b0;
        i = 0;
    end
    initial begin

        $dumpfile("huffman_dec.vcd");
        $dumpvars(0,huffman_dec);
    end
    always #1clk = ~clk;
    initial begin
        #2 rst =0;
         in =0;
       #2  in =0;
       #2  in =0;
       #2  in =1;
       #2  in =1;
       #2  in =0;
       #2  in =1;
       #2  in =1;
       #2  in =0;
       #2  in =1;
       #2  in =1;
       #2  in =1;
       #2  in =0;
       #2  in =0;
       #2  in =0;

       #2  in =1;
       #2  in =1;
       #2  in =1;
       #2  in =0;
       #2  in =0;
       #2  in =1;

       #2  in =1;
       #2  in =1;
       #2  in =1;
       #2  in =0;
       #2  in =1;
       #2  in =0;

       #2  in =1;
       #2  in =1;
       #2  in =1;
       #2  in =0;
       #2  in =1;
       #2  in =1;
       #2  in =0;

       #2  in =1;
       #2  in =1;
       #2  in =1;
       #2  in =0;
       #2  in =1;
       #2  in =1;
       #2  in =1;

       #2  in =1;
       #2  in =1;
       #2  in =1;
       #2  in =1;
       #2  in =0;
       #2  in =0;
       #2  in =0;


       #2  in =1;
       #2  in =1;
       #2  in =1;
       #2  in =1;
       #2  in =0;
       #2  in =0;
       #2  in =1;

       #2  in =1;
       #2  in =1;
       #2  in =1;
       #2  in =1;
       #2  in =0;
       #2  in =1;
       #2  in =0;

       #2  in =1;
       #2  in =1;
       #2  in =1;
       #2  in =1;
       #2  in =0;
       #2  in =1;
       #2  in =1;

       #2  in =1;
       #2  in =1;
       #2  in =1;
       #2  in =1;
       #2  in =1;
       #2  in =0;
       #2  in =0;

       #2  in =1;
       #2  in =1;
       #2  in =1;
       #2  in =1;
       #2  in =1;
       #2  in =0;
       #2  in =1;

       #2  in =1;
       #2  in =1;
       #2  in =1;
       #2  in =1;
       #2  in =1;
       #2  in =1;
       #2  in =0;

       #2  in =1;
       #2  in =1;
       #2  in =1;
       #2  in =1;
       #2  in =1;
       #2  in =1;
       #2  in =1;
       #2  in =0;

       #2  in =1;
       #2  in =1;
       #2  in =1;
       #2  in =1;
       #2  in =1;
       #2  in =1;
       #2  in =1;
       #2  in =1;
        #100$finish;
    end
endmodule
// parameter     start =        1'b0;
// parameter [1:0] S1  =       2'b00;
// parameter [1:0] S2  =       2'b01;
// parameter [1:0] S2  =       2'b01;
// parameter [1:0] S3  =       2'b10;
// parameter [2:0] S4  =      3'b110;
// parameter [5:0] S5  =   6'b111000;
// parameter [5:0] S6  =   6'b111001;
// parameter [5:0] S7  =   6'b111010;
// parameter [6:0] S8  =  7'b1110110;
// parameter [6:0] S9  =  7'b1110111;
// parameter [6:0] S10 =  7'b1111000;
// parameter [6:0] S11 =  7'b1111001;
// parameter [6:0] S12 =  7'b1111010;
// parameter [6:0] S13 =  7'b1111011;
// parameter [6:0] S14 =  7'b1111100;
// parameter [6:0] S15 =  7'b1111101;
// parameter [6:0] S16 =  7'b1111110;
// parameter [7:0] S17 = 8'b11111110;
// parameter [7:0] S18 = 8'b11111111;

Decodificador Huffman/huffman_dec.vcd
$date
	Sat Oct 01 23:36:09 2022
$end
$version
	Icarus Verilog
$end
$timescale
	1s
$end
$scope module tb $end
$scope module huffman_dec $end
$var wire 1 ! clk $end
$var wire 1 " in $end
$var wire 1 # rst $end
$var parameter 2 $ S1 $end
$var parameter 7 % S10 $end
$var parameter 7 & S11 $end
$var parameter 7 ' S12 $end
$var parameter 7 ( S13 $end
$var parameter 7 ) S14 $end
$var parameter 7 * S15 $end
$var parameter 7 + S16 $end
$var parameter 8 , S17 $end
$var parameter 8 - S18 $end
$var parameter 2 . S2 $end
$var parameter 2 / S3 $end
$var parameter 3 0 S4 $end
$var parameter 6 1 S5 $end
$var parameter 6 2 S6 $end
$var parameter 6 3 S7 $end
$var parameter 7 4 S8 $end
$var parameter 7 5 S9 $end
$var reg 8 6 buffer [7:0] $end
$var reg 4 7 counter [3:0] $end
$var reg 6 8 huffman_outp [5:0] $end
$var reg 4 9 next_counter [3:0] $end
$var reg 1 : y $end
$upscope $end
$upscope $end
$enddefinitions $end
$comment Show the parameter values. $end
$dumpall
b1110111 5
b1110110 4
b111010 3
b111001 2
b111000 1
b110 0
b10 /
b1 .
b11111111 -
b11111110 ,
b1111110 +
b1111101 *
b1111100 )
b1111011 (
b1111010 '
b1111001 &
b1111000 %
b0 $
$end
#0
$dumpvars
x:
bx 9
bx 8
bx 7
bx 6
1#
0"
0!
$end
#1
b0 9
bz 7
1!
#2
0!
0#
#3
0:
b0xxxxxxx 6
b1 9
b0 7
1!
#4
0!
#5
1:
b1 8
b0xxxxxx 6
b10 9
b1 7
1!
#6
0!
#7
0:
b1 9
b0 7
1!
#8
0!
1"
#9
1:
b10 8
b1xxxxxx 6
b10 9
b1 7
1!
#10
0!
#11
0:
b11xxxxxx 6
b1 9
b0 7
1!
#12
0!
0"
#13
1:
b11 8
b10xxxxxx 6
b10 9
b1 7
1!
#14
0!
1"
#15
0:
b1 9
b0 7
1!
#16
0!
#17
b11xxxxxx 6
b10 9
b1 7
1!
#18
0!
0"
#19
1:
b100 8
b110xxxxx 6
b11 9
b10 7
1!
#20
0!
1"
#21
0:
b1 9
b0 7
1!
#22
0!
#23
b10 9
b1 7
1!
#24
0!
#25
b111xxxxx 6
b11 9
b10 7
1!
#26
0!
0"
#27
b1110xxxx 6
b100 9
b11 7
1!
#28
0!
#29
b11100xxx 6
b101 9
b100 7
1!
#30
0!
#31
1:
b101 8
b111000xx 6
b110 9
b101 7
1!
#32
0!
1"
#33
0:
b1 9
b0 7
1!
#34
0!
#35
b10 9
b1 7
1!
#36
0!
#37
b11 9
b10 7
1!
#38
0!
0"
#39
b100 9
b11 7
1!
#40
0!
#41
b101 9
b100 7
1!
#42
0!
1"
#43
1:
b110 8
b111001xx 6
b110 9
b101 7
1!
#44
0!
#45
0:
b1 9
b0 7
1!
#46
0!
#47
b10 9
b1 7
1!
#48
0!
#49
b11 9
b10 7
1!
#50
0!
0"
#51
b100 9
b11 7
1!
#52
0!
1"
#53
b111011xx 6
b101 9
b100 7
1!
#54
0!
0"
#55
1:
b111 8
b111010xx 6
b110 9
b101 7
1!
#56
0!
1"
#57
0:
b1 9
b0 7
1!
#58
0!
#59
b10 9
b1 7
1!
#60
0!
#61
b11 9
b10 7
1!
#62
0!
0"
#63
b100 9
b11 7
1!
#64
0!
1"
#65
b101 9
b100 7
1!
#66
0!
#67
b111011xx 6
b110 9
b101 7
1!
#68
0!
0"
#69
1:
b1000 8
b1110110x 6
b111 9
b110 7
1!
#70
0!
1"
#71
0:
b1 9
b0 7
1!
#72
0!
#73
b10 9
b1 7
1!
#74
0!
#75
b11 9
b10 7
1!
#76
0!
0"
#77
b100 9
b11 7
1!
#78
0!
1"
#79
b101 9
b100 7
1!
#80
0!
#81
b110 9
b101 7
1!
#82
0!
#83
1:
b1001 8
b1110111x 6
b111 9
b110 7
1!
#84
0!
#85
0:
b1 9
b0 7
1!
#86
0!
#87
b10 9
b1 7
1!
#88
0!
#89
b11 9
b10 7
1!
#90
0!
#91
b1111111x 6
b100 9
b11 7
1!
#92
0!
0"
#93
b1111011x 6
b101 9
b100 7
1!
#94
0!
#95
b1111001x 6
b110 9
b101 7
1!
#96
0!
#97
1:
b1010 8
b1111000x 6
b111 9
b110 7
1!
#98
0!
1"
#99
0:
b1 9
b0 7
1!
#100
0!
#101
b10 9
b1 7
1!
#102
0!
#103
b11 9
b10 7
1!
#104
0!
#105
b100 9
b11 7
1!
#106
0!
0"
#107
b101 9
b100 7
1!
#108
0!
#109
b110 9
b101 7
1!
#110
0!
1"
#111
1:
b1011 8
b1111001x 6
b111 9
b110 7
1!
#112
0!
#113
0:
b1 9
b0 7
1!
#114
0!
#115
b10 9
b1 7
1!
#116
0!
#117
b11 9
b10 7
1!
#118
0!
#119
b100 9
b11 7
1!
#120
0!
0"
#121
b101 9
b100 7
1!
#122
0!
1"
#123
b1111011x 6
b110 9
b101 7
1!
#124
0!
0"
#125
1:
b1100 8
b1111010x 6
b111 9
b110 7
1!
#126
0!
1"
#127
0:
b1 9
b0 7
1!
#128
0!
#129
b10 9
b1 7
1!
#130
0!
#131
b11 9
b10 7
1!
#132
0!
#133
b100 9
b11 7
1!
#134
0!
0"
#135
b101 9
b100 7
1!
#136
0!
1"
#137
b110 9
b101 7
1!
#138
0!
#139
1:
b1101 8
b1111011x 6
b111 9
b110 7
1!
#140
0!
#141
0:
b1 9
b0 7
1!
#142
0!
#143
b10 9
b1 7
1!
#144
0!
#145
b11 9
b10 7
1!
#146
0!
#147
b100 9
b11 7
1!
#148
0!
#149
b1111111x 6
b101 9
b100 7
1!
#150
0!
0"
#151
b1111101x 6
b110 9
b101 7
1!
#152
0!
#153
1:
b1110 8
b1111100x 6
b111 9
b110 7
1!
#154
0!
1"
#155
0:
b1 9
b0 7
1!
#156
0!
#157
b10 9
b1 7
1!
#158
0!
#159
b11 9
b10 7
1!
#160
0!
#161
b100 9
b11 7
1!
#162
0!
#163
b101 9
b100 7
1!
#164
0!
0"
#165
b110 9
b101 7
1!
#166
0!
1"
#167
1:
b1111 8
b1111101x 6
b111 9
b110 7
1!
#168
0!
#169
0:
b1 9
b0 7
1!
#170
0!
#171
b10 9
b1 7
1!
#172
0!
#173
b11 9
b10 7
1!
#174
0!
#175
b100 9
b11 7
1!
#176
0!
#177
b101 9
b100 7
1!
#178
0!
#179
b1111111x 6
b110 9
b101 7
1!
#180
0!
0"
#181
1:
b10000 8
b1111110x 6
b111 9
b110 7
1!
#182
0!
1"
#183
0:
b1 9
b0 7
1!
#184
0!
#185
b10 9
b1 7
1!
#186
0!
#187
b11 9
b10 7
1!
#188
0!
#189
b100 9
b11 7
1!
#190
0!
#191
b101 9
b100 7
1!
#192
0!
#193
b110 9
b101 7
1!
#194
0!
#195
b1111111x 6
b111 9
b110 7
1!
#196
0!
0"
#197
b10001 8
1:
b11111110 6
bz 9
b111 7
1!
#198
0!
1"
#199
0:
b1 9
b0 7
1!
#200
0!
#201
b10 9
b1 7
1!
#202
0!
#203
b11 9
b10 7
1!
#204
0!
#205
b100 9
b11 7
1!
#206
0!
#207
b101 9
b100 7
1!
#208
0!
#209
b110 9
b101 7
1!
#210
0!
#211
b111 9
b110 7
1!
#212
0!
#213
1:
b10010 8
b11111111 6
bz 9
b111 7
1!
#214
0!
#215
0:
b1 9
b0 7
1!
#216
0!
#217
b10 9
b1 7
1!
#218
0!
#219
b11 9
b10 7
1!
#220
0!
#221
b100 9
b11 7
1!
#222
0!
#223
b101 9
b100 7
1!
#224
0!
#225
b110 9
b101 7
1!
#226
0!
#227
b111 9
b110 7
1!
#228
0!
#229
1:
bz 9
b111 7
1!
#230
0!
#231
0:
b1 9
b0 7
1!
#232
0!
#233
b10 9
b1 7
1!
#234
0!
#235
b11 9
b10 7
1!
#236
0!
#237
b100 9
b11 7
1!
#238
0!
#239
b101 9
b100 7
1!
#240
0!
#241
b110 9
b101 7
1!
#242
0!
#243
b111 9
b110 7
1!
#244
0!
#245
1:
bz 9
b111 7
1!
#246
0!
#247
0:
b1 9
b0 7
1!
#248
0!
#249
b10 9
b1 7
1!
#250
0!
#251
b11 9
b10 7
1!
#252
0!
#253
b100 9
b11 7
1!
#254
0!
#255
b101 9
b100 7
1!
#256
0!
#257
b110 9
b101 7
1!
#258
0!
#259
b111 9
b110 7
1!
#260
0!
#261
1:
bz 9
b111 7
1!
#262
0!
#263
0:
b1 9
b0 7
1!
#264
0!
#265
b10 9
b1 7
1!
#266
0!
#267
b11 9
b10 7
1!
#268
0!
#269
b100 9
b11 7
1!
#270
0!
#271
b101 9
b100 7
1!
#272
0!
#273
b110 9
b101 7
1!
#274
0!
#275
b111 9
b110 7
1!
#276
0!
#277
1:
bz 9
b111 7
1!
#278
0!
#279
0:
b1 9
b0 7
1!
#280
0!
#281
b10 9
b1 7
1!
#282
0!
#283
b11 9
b10 7
1!
#284
0!
#285
b100 9
b11 7
1!
#286
0!
#287
b101 9
b100 7
1!
#288
0!
#289
b110 9
b101 7
1!
#290
0!
#291
b111 9
b110 7
1!
#292
0!
#293
1:
bz 9
b111 7
1!
#294
0!
#295
0:
b1 9
b0 7
1!
#296
0!
#297
b10 9
b1 7
1!
#298
0!
#299
b11 9
b10 7
1!
#300
0!
#301
b100 9
b11 7
1!
#302
0!
#303
b101 9
b100 7
1!
#304
0!
#305
b110 9
b101 7
1!
#306
0!
#307
b111 9
b110 7
1!
#308
0!
#309
1:
bz 9
b111 7
1!
#310
0!
#311
0:
b1 9
b0 7
1!
