Log2 incompleto/log2x.sv
module log2X(input clk,
        input rst,
       input logic  [4:0] x_,
       output logic [10:0] log2_x);

    logic [4:0] exp;
    logic [4:-3] x;
    logic [127:0] mant;
    logic [4:0] log2m;
    logic y;
    logic [3:0]  aprox, i;

    always@(posedge clk,posedge rst)begin
        if(rst)begin 
            x = {x_,{3{1'b0}}};
            exp = 0;
            aprox = 5;
            log2m = 0;
            y = 0;
            i = 0;
            mant = 0;
        end
        else
            if(x[4:0] != 5'b00001)begin
                x = x >> 1;
                exp +=  1;
                mant = x;
            end
            else begin
                if(i < aprox)begin
                    mant = (mant * mant);
                    i += 1;
                end
                else begin
                    if(mant[127:96] != 1)begin
                        mant = mant >> 1;
                        log2m = log2m + 1;
                    end
                    else y = 1;
                end
            end
    end
   assign log2_x = (y ? {exp,log2m}:0);
endmodule

Log2 incompleto/testbench.sv
`include "./log2x.sv"

module tb();
    logic clk,rst;
    logic [4:0] a;
    logic [10:0] o;
    log2X log2X_(clk,rst,a,o);
    initial begin
         $dumpfile("1.vcd");
         $dumpvars(0,log2X_);
         clk = 0;
    
    end
    always #1clk = ~ clk;
    initial begin
        a = 15;
        rst  = 1;
        #2 rst = 0;

        #70$display("time = %g, log2(%.2f) = %b.%b %.2f",$time, a,o[10:5],o[4:0],(o*(2.0**-5.0)));
        a = 14;
        rst  = 1;
        #2 rst = 0;
        #70$display("time = %g, log2(%.2f) = %b.%b %.2f",$time, a,o[10:5],o[4:0],(o*(2.0**-5.0)));
        // a = 3;
        // rst  = 1;
        // #2 rst = 0;
        // #70$display("time = %g, log2(%.2f) = %b.%b %.2f",$time, a,o[10:5],o[4:0],(o*(2.0**-5.0)));
        // a = 4;
        // rst  = 1;
        // #2 rst = 0;
        // #70$display("time = %g, log2(%.2f) = %b.%b %.2f",$time, a,o[10:5],o[4:0],(o*(2.0**-5.0)));
        // a = 5;
        // rst  = 1;
        // #2 rst = 0;
        // #70$display("time = %g, log2(%.2f) = %b.%b %.2f",$time, a,o[10:5],o[4:0],(o*(2.0**-5.0)));
        // a = 6;
        // rst  = 1;
        // #2 rst = 0;
        // #70$display("time = %g, log2(%.2f) = %b.%b %.2f",$time, a,o[10:5],o[4:0],(o*(2.0**-5.0)));
        // a = 7;
        // rst  = 1;
        // #2 rst = 0;
        // #70$display("time = %g, log2(%.2f) = %b.%b %.2f",$time, a,o[10:5],o[4:0],(o*(2.0**-5.0)));
        // a = 8;
        // rst  = 1;
        // #2 rst = 0;
        // #70$display("time = %g, log2(%.2f) = %b.%b %.2f",$time, a,o[10:5],o[4:0],(o*(2.0**-5.0)));
        // a = 9;
        // rst  = 1;
        // #2 rst = 0;
        // #70$display("time = %g, log2(%.2f) = %b.%b %.2f",$time, a,o[10:5],o[4:0],(o*(2.0**-5.0)));
        // a = 10;
        // rst  = 1;
        // #2 rst = 0;
        // #70$display("time = %g, log2(%.2f) = %b.%b %.2f",$time, a,o[10:5],o[4:0],(o*(2.0**-5.0)));
        // a = 11;
        // rst  = 1;
        // #2 rst = 0;
        // #70$display("time = %g, log2(%.2f) = %b.%b %.2f",$time, a,o[10:5],o[4:0],(o*(2.0**-5.0)));
        // a = 12;
        // rst  = 1;
        // #2 rst = 0;
        // #70$display("time = %g, log2(%.2f) = %b.%b %.2f",$time, a,o[10:5],o[4:0],(o*(2.0**-5.0)));
        // a = 13;
        // rst  = 1;
        // #2 rst = 0;
        // #70$display("time = %g, log2(%.2f) = %b.%b %.2f",$time, a,o[10:5],o[4:0],(o*(2.0**-5.0)));
        // a = 14;
        // rst  = 1;
        // #2 rst = 0;
        // #70$display("time = %g, log2(%.2f) = %b.%b %.2f",$time, a,o[10:5],o[4:0],(o*(2.0**-5.0)));
        // a = 17;
        // rst  = 1;
        // #2 rst = 0;
        // #70$display("time = %g, log2(%.2f) = %b.%b %.2f",$time, a,o[10:5],o[4:0],(o*(2.0**-5.0)));
    end
    initial #100000$finish;


endmodule

Log2 incompleto/1.vcd
$date
	Mon Oct 10 21:53:49 2022
$end
$version
	Icarus Verilog
$end
$timescale
	1s
$end
$scope module tb $end
$scope module log2X_ $end
$var wire 1 ! clk $end
$var wire 1 " rst $end
$var wire 5 # x_ [4:0] $end
$var wire 11 $ log2_x [10:0] $end
$var reg 4 % aprox [3:0] $end
$var reg 5 & exp [4:0] $end
$var reg 4 ' i [3:0] $end
$var reg 5 ( log2m [4:0] $end
$var reg 128 ) mant [127:0] $end
$var reg 8 * x [4:-3] $end
$var reg 1 + y $end
$upscope $end
$upscope $end
$enddefinitions $end
$comment Show the parameter values. $end
$dumpall
$end
#0
$dumpvars
0+
b1111000 *
b0 )
b0 (
b0 '
b0 &
b101 %
b0 $
b1111 #
1"
0!
$end
#1
1!
#2
0!
0"
#3
b111100 )
b1 &
b111100 *
1!
#4
0!
#5
b11110 )
b10 &
b11110 *
1!
#6
0!
#7
b1111 )
b11 &
b1111 *
1!
#8
0!
#9
b1 '
b11100001 )
1!
#10
0!
#11
b10 '
b1100010111000001 )
1!
#12
0!
#13
b11 '
b10011000110000101001101110000001 )
1!
#14
0!
#15
b100 '
b101101100100111101011001001100100111101111110010111011100000001 )
1!
#16
0!
#17
b101 '
b100000011101010011101011011010111111010001111010000011100111110101001101101000011011010000000100110001010000111110111000000001 )
1!
#18
0!
#19
b1 (
b10000001110101001110101101101011111101000111101000001110011111010100110110100001101101000000010011000101000011111011100000000 )
1!
#20
0!
#21
b10 (
b1000000111010100111010110110101111110100011110100000111001111101010011011010000110110100000001001100010100001111101110000000 )
1!
#22
0!
#23
b11 (
b100000011101010011101011011010111111010001111010000011100111110101001101101000011011010000000100110001010000111110111000000 )
1!
#24
0!
#25
b100 (
b10000001110101001110101101101011111101000111101000001110011111010100110110100001101101000000010011000101000011111011100000 )
1!
#26
0!
#27
b101 (
b1000000111010100111010110110101111110100011110100000111001111101010011011010000110110100000001001100010100001111101110000 )
1!
#28
0!
#29
b110 (
b100000011101010011101011011010111111010001111010000011100111110101001101101000011011010000000100110001010000111110111000 )
1!
#30
0!
#31
b111 (
b10000001110101001110101101101011111101000111101000001110011111010100110110100001101101000000010011000101000011111011100 )
1!
#32
0!
#33
b1000 (
b1000000111010100111010110110101111110100011110100000111001111101010011011010000110110100000001001100010100001111101110 )
1!
#34
0!
#35
b1001 (
b100000011101010011101011011010111111010001111010000011100111110101001101101000011011010000000100110001010000111110111 )
1!
#36
0!
#37
b1010 (
b10000001110101001110101101101011111101000111101000001110011111010100110110100001101101000000010011000101000011111011 )
1!
#38
0!
#39
b1011 (
b1000000111010100111010110110101111110100011110100000111001111101010011011010000110110100000001001100010100001111101 )
1!
#40
0!
#41
b1100 (
b100000011101010011101011011010111111010001111010000011100111110101001101101000011011010000000100110001010000111110 )
1!
#42
0!
#43
b1101 (
b10000001110101001110101101101011111101000111101000001110011111010100110110100001101101000000010011000101000011111 )
1!
#44
0!
#45
b1110 (
b1000000111010100111010110110101111110100011110100000111001111101010011011010000110110100000001001100010100001111 )
1!
#46
0!
#47
b1111 (
b100000011101010011101011011010111111010001111010000011100111110101001101101000011011010000000100110001010000111 )
1!
#48
0!
#49
b10000 (
b10000001110101001110101101101011111101000111101000001110011111010100110110100001101101000000010011000101000011 )
1!
#50
0!
#51
b10001 (
b1000000111010100111010110110101111110100011110100000111001111101010011011010000110110100000001001100010100001 )
1!
#52
0!
#53
b10010 (
b100000011101010011101011011010111111010001111010000011100111110101001101101000011011010000000100110001010000 )
1!
#54
0!
#55
b10011 (
b10000001110101001110101101101011111101000111101000001110011111010100110110100001101101000000010011000101000 )
1!
#56
0!
#57
b10100 (
b1000000111010100111010110110101111110100011110100000111001111101010011011010000110110100000001001100010100 )
1!
#58
0!
#59
b10101 (
b100000011101010011101011011010111111010001111010000011100111110101001101101000011011010000000100110001010 )
1!
#60
0!
#61
b10110 (
b10000001110101001110101101101011111101000111101000001110011111010100110110100001101101000000010011000101 )
1!
#62
0!
#63
b10111 (
b1000000111010100111010110110101111110100011110100000111001111101010011011010000110110100000001001100010 )
1!
#64
0!
#65
b11000 (
b100000011101010011101011011010111111010001111010000011100111110101001101101000011011010000000100110001 )
1!
#66
0!
#67
b11001 (
b10000001110101001110101101101011111101000111101000001110011111010100110110100001101101000000010011000 )
1!
#68
0!
#69
b11010 (
b1000000111010100111010110110101111110100011110100000111001111101010011011010000110110100000001001100 )
1!
#70
0!
#71
b11011 (
b100000011101010011101011011010111111010001111010000011100111110101001101101000011011010000000100110 )
1!
#72
b0 )
b0 '
b0 (
b0 &
b1110000 *
0!
1"
b1110 #
#73
1!
#74
0!
0"
#75
b111000 )
b1 &
b111000 *
1!
#76
0!
#77
b11100 )
b10 &
b11100 *
1!
#78
0!
#79
b1110 )
b11 &
b1110 *
1!
#80
0!
#81
b1 '
b11000100 )
1!
#82
0!
#83
b10 '
b1001011000010000 )
1!
#84
0!
#85
b11 '
b1010111111101101100000100000000 )
1!
#86
0!
#87
b100 '
b1111000111001101001010000010101111101100000010000000000000000 )
1!
#88
0!
#89
b101 '
b11100100011000111110101000001100000011110000110011010110000110111010010001001110110000000100000000000000000000000000000000 )
1!
#90
0!
#91
b1 (
b1110010001100011111010100000110000001111000011001101011000011011101001000100111011000000010000000000000000000000000000000 )
1!
#92
0!
#93
b10 (
b111001000110001111101010000011000000111100001100110101100001101110100100010011101100000001000000000000000000000000000000 )
1!
#94
0!
#95
b11 (
b11100100011000111110101000001100000011110000110011010110000110111010010001001110110000000100000000000000000000000000000 )
1!
#96
0!
#97
b100 (
b1110010001100011111010100000110000001111000011001101011000011011101001000100111011000000010000000000000000000000000000 )
1!
#98
0!
#99
b101 (
b111001000110001111101010000011000000111100001100110101100001101110100100010011101100000001000000000000000000000000000 )
1!
#100
0!
#101
b110 (
b11100100011000111110101000001100000011110000110011010110000110111010010001001110110000000100000000000000000000000000 )
1!
#102
0!
#103
b111 (
b1110010001100011111010100000110000001111000011001101011000011011101001000100111011000000010000000000000000000000000 )
1!
#104
0!
#105
b1000 (
b111001000110001111101010000011000000111100001100110101100001101110100100010011101100000001000000000000000000000000 )
1!
#106
0!
#107
b1001 (
b11100100011000111110101000001100000011110000110011010110000110111010010001001110110000000100000000000000000000000 )
1!
#108
0!
#109
b1010 (
b1110010001100011111010100000110000001111000011001101011000011011101001000100111011000000010000000000000000000000 )
1!
#110
0!
#111
b1011 (
b111001000110001111101010000011000000111100001100110101100001101110100100010011101100000001000000000000000000000 )
1!
#112
0!
#113
b1100 (
b11100100011000111110101000001100000011110000110011010110000110111010010001001110110000000100000000000000000000 )
1!
#114
0!
#115
b1101 (
b1110010001100011111010100000110000001111000011001101011000011011101001000100111011000000010000000000000000000 )
1!
#116
0!
#117
b1110 (
b111001000110001111101010000011000000111100001100110101100001101110100100010011101100000001000000000000000000 )
1!
#118
0!
#119
b1111 (
b11100100011000111110101000001100000011110000110011010110000110111010010001001110110000000100000000000000000 )
1!
#120
0!
#121
b10000 (
b1110010001100011111010100000110000001111000011001101011000011011101001000100111011000000010000000000000000 )
1!
#122
0!
#123
b10001 (
b111001000110001111101010000011000000111100001100110101100001101110100100010011101100000001000000000000000 )
1!
#124
0!
#125
b10010 (
b11100100011000111110101000001100000011110000110011010110000110111010010001001110110000000100000000000000 )
1!
#126
0!
#127
b10011 (
b1110010001100011111010100000110000001111000011001101011000011011101001000100111011000000010000000000000 )
1!
#128
0!
#129
b10100 (
b111001000110001111101010000011000000111100001100110101100001101110100100010011101100000001000000000000 )
1!
#130
0!
#131
b10101 (
b11100100011000111110101000001100000011110000110011010110000110111010010001001110110000000100000000000 )
1!
#132
0!
#133
b10110 (
b1110010001100011111010100000110000001111000011001101011000011011101001000100111011000000010000000000 )
1!
#134
0!
#135
b10111 (
b111001000110001111101010000011000000111100001100110101100001101110100100010011101100000001000000000 )
1!
#136
0!
#137
b11000 (
b11100100011000111110101000001100000011110000110011010110000110111010010001001110110000000100000000 )
1!
#138
0!
#139
b11001 (
b1110010001100011111010100000110000001111000011001101011000011011101001000100111011000000010000000 )
1!
#140
0!
#141
b1111001 $
1+
1!
