Log2 incompleto/normalizacao.sv



module log2(input  logic clk,rst,
            input  logic [8:0] inputValue,
            output logic [8:0] valueNormalized
            );
    logic [8:0] expoente_j;
    logic [8:0] _inputValue_;
    logic [2:0] base2;

    logic y;
    always@(posedge clk)begin
        if(_inputValue_[8] != 1'b1 && expoente_j !=0)begin
            _inputValue_ = _inputValue_ << 1;
            expoente_j = expoente_j - 1;
        end
        else if(y)begin
            base2 = base2 >> (expoente_j);
            y =0;
        end
        else
            valueNormalized = inputValue*(base2);
    end

    always@(negedge rst) begin
        if(~rst)begin
            expoente_j = 8;
            _inputValue_ = inputValue;
            valueNormalized = 0;
            y = 1;
            base2 = 3'b100;
        end
    end
endmodule

Log2 incompleto/testbench.sv
`include "./normalizacao.sv"
parameter E_int = 4;
parameter D_frac = 3;
module tb();
    logic clk,rst;
    logic signed [8:0] valor;
    logic [8:0] saida;
    log2 normalizacao(clk,rst,valor,saida);
    initial begin
         $monitor("%d", (saida));
         clk = 0;
         rst = 0;
         $dumpfile("normalizacao.vcd");
         $dumpvars(0,normalizacao);
    end
    always #1clk = ~ clk;
    initial begin
       valor = 5;
        // valor = 4.5;
        rst= 1;
        #1rst= 0;
    
    end
    initial #100 $finish;


endmodule

Log2 incompleto/normalizacao.vcd
$date
	Sat Oct 01 10:43:20 2022
$end
$version
	Icarus Verilog
$end
$timescale
	1s
$end
$scope module tb $end
$scope module normalizacao $end
$var wire 1 ! clk $end
$var wire 9 " inputValue [8:0] $end
$var wire 1 # rst $end
$var reg 9 $ _inputValue_ [8:0] $end
$var reg 3 % base2 [2:0] $end
$var reg 9 & expoente_j [8:0] $end
$var reg 9 ' valueNormalized [8:0] $end
$var reg 1 ( y $end
$upscope $end
$upscope $end
$enddefinitions $end
$comment Show the parameter values. $end
$dumpall
$end
#0
$dumpvars
x(
bx '
bx &
bx %
bx $
1#
b101 "
0!
$end
#1
b100 %
1(
b0 '
b101 $
b1000 &
0#
1!
#2
0!
#3
b111 &
b1010 $
1!
#4
0!
#5
b110 &
b10100 $
1!
#6
0!
#7
b101 &
b101000 $
1!
#8
0!
#9
b100 &
b1010000 $
1!
#10
0!
#11
b11 &
b10100000 $
1!
#12
0!
#13
b10 &
b101000000 $
1!
#14
0!
#15
0(
b1 %
1!
#16
0!
#17
b101 '
1!
